hypgeo/__init___.py
hypgeo/complex_plane.py
hypgeo/geometry.py
hypgeo/moebius.py
hypgeo/transformations.py
hypgeo/unittest_complex_plane.py
hypgeo/unittest_moebius.py
hypgeo/unittest_transformation.py
hypgeo/helpers/__init__.py
hypgeo/helpers/field.py
hypgeo/helpers/group.py
hypgeo-1.3.dist-info/LICENSE
hypgeo-1.3.dist-info/METADATA
hypgeo-1.3.dist-info/WHEEL
hypgeo-1.3.dist-info/top_level.txt
hypgeo-1.3.dist-info/RECORD
